factorio_rcon/__init__.py
factorio_rcon/_factorio_rcon.py
factorio_rcon/py.typed
factorio_rcon_py-2.1.2.dist-info/LICENSE
factorio_rcon_py-2.1.2.dist-info/METADATA
factorio_rcon_py-2.1.2.dist-info/WHEEL
factorio_rcon_py-2.1.2.dist-info/top_level.txt
factorio_rcon_py-2.1.2.dist-info/RECORD
