Metadata-Version: 2.1
Name: factorio-rcon-py
Version: 2.1.2
Summary: A simple Factorio RCON client
Author: mark9064
License: GNU LESSER GENERAL PUBLIC LICENSE
Project-URL: homepage, https://github.com/mark9064/factorio-rcon-py
Classifier: Programming Language :: Python :: 3
Classifier: License :: OSI Approved :: GNU Lesser General Public License v2 (LGPLv2)
Classifier: Operating System :: OS Independent
Classifier: Development Status :: 5 - Production/Stable
Classifier: Natural Language :: English
Requires-Python: >=3.8
License-File: LICENSE
Provides-Extra: async
Requires-Dist: anyio <5.0,>=4.0 ; extra == 'async'
